mtcli_pa/__init__.py
mtcli_pa/bo.py
mtcli_pa/conf.py
mtcli_pa/gp.py
mtcli_pa/ln.py
mtcli_pa/pa.py
mtcli_pa/tr.py
mtcli_pa-1.0.4.dist-info/entry_points.txt
mtcli_pa-1.0.4.dist-info/LICENSE
mtcli_pa-1.0.4.dist-info/METADATA
mtcli_pa-1.0.4.dist-info/WHEEL
mtcli_pa-1.0.4.dist-info/RECORD
