Metadata-Version: 2.3
Name: mtcli-pa
Version: 1.0.4
Summary: Plugin mtcli para calcular níveis e projeções de price action
License: GPL-3.0
Author: Valmir França da Silva
Author-email: vfranca3@gmail.com
Requires-Python: >=3.11,<3.14.0
Classifier: License :: OSI Approved :: GNU General Public License v3 (GPLv3)
Classifier: Programming Language :: Python :: 3
Classifier: Programming Language :: Python :: 3.11
Classifier: Programming Language :: Python :: 3.12
Classifier: Programming Language :: Python :: 3.13
Requires-Dist: mtcli (>=1.18.1)
Project-URL: Documentation, https://vfranca.github.io/mtcli-pa
Project-URL: Homepage, https://github.com/vfranca/mtcli-pa
Project-URL: Repository, https://github.com/vfranca/mtcli-pa
Project-URL: issues, https://github.com/vfranca/mtcli-pa/issues
